iam_provider/iam_provider.py
iam_provider/manifest.toml
iam_provider/test_iam_provider.py
opsbox_iam_provider-0.1.6.dist-info/licenses/LICENCE.txt
opsbox_iam_provider-0.1.6.dist-info/METADATA
opsbox_iam_provider-0.1.6.dist-info/WHEEL
opsbox_iam_provider-0.1.6.dist-info/entry_points.txt
opsbox_iam_provider-0.1.6.dist-info/top_level.txt
opsbox_iam_provider-0.1.6.dist-info/RECORD
